{"data":{"config":{"elements":{"title":{"value":"Aaron Collier"},"splash_image":{"value":[{"url":"https://assets-us-01.kc-usercontent.com:443/3fcf700a-30e8-4d1d-9e64-43193a89fe7a/259d5f15-d354-4701-a299-91cbb7cdf8ce/the-trees-in-the-fall-2052252_640.jpg"}]},"blog_logo":{"value":[{"url":"https://assets-us-01.kc-usercontent.com:443/3fcf700a-30e8-4d1d-9e64-43193a89fe7a/8af6ebfc-b92f-4603-90f5-5d3dda5d8c3d/quixote-small.jpg"}]},"metadata__description":{"value":"Articles and interesting things."},"socialmedia":{"value":"mailto:aaron@collier.cz,https://github.com/CollierCZ"},"base_url":{"value":"https://collier.cz"}}},"articles":{"edges":[{"node":{"fields":{"slug":"brno","tags":["brno"," czech"," city"],"category":"Education","date":"2018-11-23T00:00:00.000Z"},"elements":{"metadata__description":{"value":"Some things about Brno"},"title":{"value":"Brno"},"teaser":{"value":[{"url":"https://assets-us-01.kc-usercontent.com:443/3fcf700a-30e8-4d1d-9e64-43193a89fe7a/dbddc708-ee5b-4aaa-9874-19b399a86dad/brno-square.jpg"}]}}}}]}},"pageContext":{"tag":" czech","nodes":[{"fields":{"slug":"brno","tags":["brno"," czech"," city"],"category":"Education"}}],"page":1,"pages":1,"total":1,"limit":3}}